COPYING
CREDITS
MANIFEST.in
NEWS
README
setup.cfg
setup.py
TracBzr.egg-info/PKG-INFO
TracBzr.egg-info/SOURCES.txt
TracBzr.egg-info/dependency_links.txt
TracBzr.egg-info/entry_points.txt
TracBzr.egg-info/top_level.txt
tracbzr/__init__.py
tracbzr/backend.py