Metadata-Version: 1.0
Name: TracBzr
Version: 0.3.3
Summary: Bazaar plugin for Trac
Home-page: http://launchpad.net/trac-bzr
Author: Trac Bazaar Team
Author-email: trac-bzr-team@lists.launchpad.net
License: GPL
Keywords: trac vcs plugin bazaar bzr
Platform: UNKNOWN
Classifier: Development Status :: 4 - Beta
Classifier: Environment :: Plugins
Classifier: Environment :: Web Environment
Classifier: Framework :: Trac
Classifier: Intended Audience :: Developers
Classifier: License :: OSI Approved :: GNU General Public License (GPL)
Classifier: Natural Language :: English
Classifier: Operating System :: OS Independent
Classifier: Programming Language :: Python
Classifier: Programming Language :: Python :: 2
Classifier: Topic :: Internet :: WWW/HTTP :: Dynamic Content
Classifier: Topic :: Software Development :: Version Control
